{
  "runs": [
    {
      "crawl_time": "23-04",
      "items": [
        {
          "platform_id": "toutiao",
          "platform_name": "今日头条",
          "rank": 1,
          "title": "时隔50年全班同学再聚会一个都没少",
          "url": "https://www.toutiao.com/trending/7631119535143354410/"
        },
        {
          "platform_id": "toutiao",
          "platform_name": "今日头条",
          "rank": 2,
          "title": "日本7.7级强震影响有多大",
          "url": "https://www.toutiao.com/trending/7631198112081514026/"
        },
        {
          "platform_id": "toutiao",
          "platform_name": "今日头条",
          "rank": 3,
          "title": "一季度服务业经济“开门红”",
          "url": "https://www.toutiao.com/trending/7631192494792937011/"
        },
        {
          "platform_id": "toutiao",
          "platform_name": "今日头条",
          "rank": 4,
          "title": "台空军喊话 解放军强硬回应“闭嘴”",
          "url": "https://www.toutiao.com/trending/7630315668839350335/"
        },
        {
          "platform_id": "toutiao",
          "platform_name": "今日头条",
          "rank": 5,
          "title": "海信硬杠格力：多三两铜就敢多卖500",
          "url": "https://www.toutiao.com/trending/7630769619493929003/"
        },
        {
          "platform_id": "toutiao",
          "platform_name": "今日头条",
          "rank": 6,
          "title": "特朗普：停火到期后将继续轰炸伊朗",
          "url": "https://www.toutiao.com/trending/7630112244986334726/"
        },
        {
          "platform_id": "toutiao",
          "platform_name": "今日头条",
          "rank": 7,
          "title": "伊朗称已为战事重新爆发做好准备",
          "url": "https://www.toutiao.com/trending/7630242126521008169/"
        },
        {
          "platform_id": "toutiao",
          "platform_name": "今日头条",
          "rank": 8,
          "title": "巴萨官方回应“青训网站不当用图”",
          "url": "https://www.toutiao.com/trending/7630821273954435115/"
        },
        {
          "platform_id": "toutiao",
          "platform_name": "今日头条",
          "rank": 9,
          "title": "中方：希望欧方不要低估中方坚定决心",
          "url": "https://www.toutiao.com/trending/7630810825251274815/"
        },
        {
          "platform_id": "toutiao",
          "platform_name": "今日头条",
          "rank": 10,
          "title": "中国运导弹原料船被美扣押？中方回应",
          "url": "https://www.toutiao.com/trending/7631113094080499227/"
        },
        {
          "platform_id": "toutiao",
          "platform_name": "今日头条",
          "rank": 11,
          "title": "张雪前老板娘的车队夺冠了",
          "url": "https://www.toutiao.com/trending/7630737424226205738/"
        },
        {
          "platform_id": "toutiao",
          "platform_name": "今日头条",
          "rank": 12,
          "title": "四川绵阳游仙区一厂房大火？不实",
          "url": "https://www.toutiao.com/trending/7630780696307466278/"
        },
        {
          "platform_id": "toutiao",
          "platform_name": "今日头条",
          "rank": 13,
          "title": "美军集结三航母 伊朗能扛住吗",
          "url": "https://www.toutiao.com/trending/7630298529822736426/"
        },
        {
          "platform_id": "toutiao",
          "platform_name": "今日头条",
          "rank": 14,
          "title": "食管癌：被“烫”出来的食管危机",
          "url": "https://www.toutiao.com/trending/7630310584328765483/"
        },
        {
          "platform_id": "toutiao",
          "platform_name": "今日头条",
          "rank": 15,
          "title": "新增5个国家码接入微信支付",
          "url": "https://www.toutiao.com/trending/7630664099249340458/"
        },
        {
          "platform_id": "toutiao",
          "platform_name": "今日头条",
          "rank": 16,
          "title": "孙俪儿子化个妆直接能演甄嬛了",
          "url": "https://www.toutiao.com/trending/7630653146561855497/"
        },
        {
          "platform_id": "toutiao",
          "platform_name": "今日头条",
          "rank": 17,
          "title": "宁德时代发布第三代神行超充电池",
          "url": "https://www.toutiao.com/trending/7630684576390332454/"
        },
        {
          "platform_id": "toutiao",
          "platform_name": "今日头条",
          "rank": 18,
          "title": "日学者：超级地震或致日本国家崩溃",
          "url": "https://www.toutiao.com/trending/7630755864559960091/"
        },
        {
          "platform_id": "toutiao",
          "platform_name": "今日头条",
          "rank": 19,
          "title": "桂林山水甲天下石碑被淹",
          "url": "https://www.toutiao.com/trending/7631126744297013299/"
        },
        {
          "platform_id": "toutiao",
          "platform_name": "今日头条",
          "rank": 20,
          "title": "柬埔寨国王在京手术 洪森携子看望",
          "url": "https://www.toutiao.com/trending/7630628101822890022/"
        },
        {
          "platform_id": "toutiao",
          "platform_name": "今日头条",
          "rank": 21,
          "title": "日本的挑衅只会让中国人同仇敌忾",
          "url": "https://www.toutiao.com/trending/7631141292038176804/"
        },
        {
          "platform_id": "toutiao",
          "platform_name": "今日头条",
          "rank": 22,
          "title": "国内油价迎今年首次下调",
          "url": "https://www.toutiao.com/trending/7630377054950785030/"
        },
        {
          "platform_id": "toutiao",
          "platform_name": "今日头条",
          "rank": 23,
          "title": "身体出现6种情况可能是肺癌的信号",
          "url": "https://www.toutiao.com/trending/7631015243917852699/"
        },
        {
          "platform_id": "toutiao",
          "platform_name": "今日头条",
          "rank": 24,
          "title": "日本女主播遇7.7级地震一秒变脸",
          "url": "https://www.toutiao.com/trending/7630863108064542774/"
        },
        {
          "platform_id": "toutiao",
          "platform_name": "今日头条",
          "rank": 25,
          "title": "你如何看中国馒头在国外走红",
          "url": "https://www.toutiao.com/trending/7631053981633052698/"
        },
        {
          "platform_id": "toutiao",
          "platform_name": "今日头条",
          "rank": 26,
          "title": "外交部发言人三问日本",
          "url": "https://www.toutiao.com/trending/7630772597357510692/"
        },
        {
          "platform_id": "toutiao",
          "platform_name": "今日头条",
          "rank": 27,
          "title": "无人机侵入致京沪高铁一列车故障晚点",
          "url": "https://www.toutiao.com/trending/7630987808912228378/"
        },
        {
          "platform_id": "toutiao",
          "platform_name": "今日头条",
          "rank": 28,
          "title": "特朗普政府遭民主党“组合拳”",
          "url": "https://www.toutiao.com/trending/7631179561052409407/"
        },
        {
          "platform_id": "toutiao",
          "platform_name": "今日头条",
          "rank": 29,
          "title": "硬化后地面掉渣 男子投诉混凝土商家",
          "url": "https://www.toutiao.com/trending/7631138774408134662/"
        },
        {
          "platform_id": "toutiao",
          "platform_name": "今日头条",
          "rank": 30,
          "title": "苹果换帅：选择匹配下一阶段问题的人",
          "url": "https://www.toutiao.com/trending/7631161454471462955/"
        },
        {
          "platform_id": "toutiao",
          "platform_name": "今日头条",
          "rank": 31,
          "title": "姚晨怒斥深圳违规私转患者救护车",
          "url": "https://www.toutiao.com/trending/7631146954353197092/"
        },
        {
          "platform_id": "toutiao",
          "platform_name": "今日头条",
          "rank": 32,
          "title": "泰国少女泼水节遭士兵尾随进公厕性侵",
          "url": "https://www.toutiao.com/trending/7630374803942965299/"
        },
        {
          "platform_id": "toutiao",
          "platform_name": "今日头条",
          "rank": 33,
          "title": "盾构机“沧渊号”掘进突破3000米",
          "url": "https://www.toutiao.com/trending/7631079645718609939/"
        },
        {
          "platform_id": "toutiao",
          "platform_name": "今日头条",
          "rank": 34,
          "title": "台湾新党副主席李胜峰谈民意变化",
          "url": "https://www.toutiao.com/trending/7630689073435361289/"
        },
        {
          "platform_id": "toutiao",
          "platform_name": "今日头条",
          "rank": 35,
          "title": "餐厅突发火灾 司机开铲车救2个孩子",
          "url": "https://www.toutiao.com/trending/7630289401108578358/"
        },
        {
          "platform_id": "toutiao",
          "platform_name": "今日头条",
          "rank": 36,
          "title": "欧盟将强制手机平板配备可更换电池",
          "url": "https://www.toutiao.com/trending/7630371983541141514/"
        },
        {
          "platform_id": "toutiao",
          "platform_name": "今日头条",
          "rank": 37,
          "title": "退休局长“隐居孤岛”11年",
          "url": "https://www.toutiao.com/trending/7631155267652534326/"
        },
        {
          "platform_id": "toutiao",
          "platform_name": "今日头条",
          "rank": 38,
          "title": "卫生院用瓶子自制神器方便老人排号",
          "url": "https://www.toutiao.com/trending/7630739542450094123/"
        },
        {
          "platform_id": "toutiao",
          "platform_name": "今日头条",
          "rank": 39,
          "title": "老中医现场针灸治疗后患者当场落泪",
          "url": "https://www.toutiao.com/trending/7630055937160495110/"
        },
        {
          "platform_id": "toutiao",
          "platform_name": "今日头条",
          "rank": 40,
          "title": "福州千年古榕能容纳千人乘凉",
          "url": "https://www.toutiao.com/trending/7630861533051944969/"
        },
        {
          "platform_id": "toutiao",
          "platform_name": "今日头条",
          "rank": 41,
          "title": "刚果：明年4月起禁止美元现金交易",
          "url": "https://www.toutiao.com/trending/7631131841846378523/"
        },
        {
          "platform_id": "toutiao",
          "platform_name": "今日头条",
          "rank": 42,
          "title": "郑丽文：两岸强强联手可造福全世界",
          "url": "https://www.toutiao.com/trending/7630842333692854299/"
        },
        {
          "platform_id": "toutiao",
          "platform_name": "今日头条",
          "rank": 43,
          "title": "专家：大盘短期进入震荡阶段",
          "url": "https://www.toutiao.com/trending/7630588846707097619/"
        },
        {
          "platform_id": "toutiao",
          "platform_name": "今日头条",
          "rank": 44,
          "title": "张雪建议实行摩托车驾照分级管理",
          "url": "https://www.toutiao.com/trending/7630580188694233142/"
        },
        {
          "platform_id": "toutiao",
          "platform_name": "今日头条",
          "rank": 45,
          "title": "高一男生跳高2米引全场沸腾",
          "url": "https://www.toutiao.com/trending/7630859314945720363/"
        },
        {
          "platform_id": "toutiao",
          "platform_name": "今日头条",
          "rank": 46,
          "title": "老奶奶拎着书包边赶狗边护着两个娃",
          "url": "https://www.toutiao.com/trending/7631102833539137579/"
        },
        {
          "platform_id": "toutiao",
          "platform_name": "今日头条",
          "rank": 47,
          "title": "郑毓煌：中国的大学应向全社会开放",
          "url": "https://www.toutiao.com/trending/7630385855836291135/"
        },
        {
          "platform_id": "toutiao",
          "platform_name": "今日头条",
          "rank": 48,
          "title": "日本为何急着变身“战争贩子”",
          "url": "https://www.toutiao.com/trending/7631186791336250899/"
        },
        {
          "platform_id": "toutiao",
          "platform_name": "今日头条",
          "rank": 49,
          "title": "苹果更换CEO原因首次曝光",
          "url": "https://www.toutiao.com/trending/7630985564023488555/"
        },
        {
          "platform_id": "toutiao",
          "platform_name": "今日头条",
          "rank": 50,
          "title": "陈泽仕中超处子球 泰山2-1逆转津门虎",
          "url": "https://www.toutiao.com/trending/7630188997322653706/"
        },
        {
          "platform_id": "thepaper",
          "platform_name": "澎湃新闻",
          "rank": 1,
          "title": "长沙一岁幼童在湿地公园玩耍坠入窨井，管理方：已整改，愿商讨赔偿",
          "url": "https://www.thepaper.cn/newsDetail_forward_33012252"
        },
        {
          "platform_id": "thepaper",
          "platform_name": "澎湃新闻",
          "rank": 2,
          "title": "西班牙提案、意大利变脸、百万民众联署：欧洲对以色列态度加速转向",
          "url": "https://www.thepaper.cn/newsDetail_forward_33012224"
        },
        {
          "platform_id": "thepaper",
          "platform_name": "澎湃新闻",
          "rank": 3,
          "title": "真假洋牌丨起底NeuWell辅酶Q10：违规添加PQQ，上市未经审批",
          "url": "https://www.thepaper.cn/newsDetail_forward_32992535"
        },
        {
          "platform_id": "thepaper",
          "platform_name": "澎湃新闻",
          "rank": 4,
          "title": "爱奇艺AI艺人库争议背后：为何要推进，如何保证演员和观众权益？",
          "url": "https://www.thepaper.cn/newsDetail_forward_33011865"
        },
        {
          "platform_id": "thepaper",
          "platform_name": "澎湃新闻",
          "rank": 5,
          "title": "重访“新闻名篇”丨60年了，为何还对焦裕禄念念不忘？",
          "url": "https://www.thepaper.cn/newsDetail_forward_33009718"
        },
        {
          "platform_id": "thepaper",
          "platform_name": "澎湃新闻",
          "rank": 6,
          "title": "山东一法院干警配偶刚成立公司拍得银行六千万债权引质疑，多方回应",
          "url": "https://www.thepaper.cn/newsDetail_forward_33017388"
        },
        {
          "platform_id": "thepaper",
          "platform_name": "澎湃新闻",
          "rank": 7,
          "title": "日本通过内阁决议正式允许出口杀伤性武器",
          "url": "https://www.thepaper.cn/newsDetail_forward_33016180"
        },
        {
          "platform_id": "thepaper",
          "platform_name": "澎湃新闻",
          "rank": 8,
          "title": "高市早苗向靖国神社献祭品",
          "url": "https://www.thepaper.cn/newsDetail_forward_33015014"
        },
        {
          "platform_id": "thepaper",
          "platform_name": "澎湃新闻",
          "rank": 9,
          "title": "上海楼市“金三银四”实探：二手房置换链向上传导，“卖旧买新”激活新房需求",
          "url": "https://www.thepaper.cn/newsDetail_forward_33011796"
        },
        {
          "platform_id": "thepaper",
          "platform_name": "澎湃新闻",
          "rank": 10,
          "title": "澎湃回声｜临沂回应“一法院干警配偶刚成立公司拍得银行六千万债权”：组成联合调查组",
          "url": "https://www.thepaper.cn/newsDetail_forward_33018478"
        },
        {
          "platform_id": "thepaper",
          "platform_name": "澎湃新闻",
          "rank": 11,
          "title": "外交部回应高市向靖国神社献祭品：日方此举是对自身罪责的逃避",
          "url": "https://www.thepaper.cn/newsDetail_forward_33018219"
        },
        {
          "platform_id": "thepaper",
          "platform_name": "澎湃新闻",
          "rank": 12,
          "title": "马上评｜巨额打赏、“年少大方”，谁该反思？",
          "url": "https://www.thepaper.cn/newsDetail_forward_33017045"
        },
        {
          "platform_id": "thepaper",
          "platform_name": "澎湃新闻",
          "rank": 13,
          "title": "张治中将军女儿、著名侨领张素久在美国逝世，享年91岁",
          "url": "https://www.thepaper.cn/newsDetail_forward_33017846"
        },
        {
          "platform_id": "thepaper",
          "platform_name": "澎湃新闻",
          "rank": 14,
          "title": "日本自卫队训练场爆炸事故致3死1重伤",
          "url": "https://www.thepaper.cn/newsDetail_forward_33017051"
        },
        {
          "platform_id": "thepaper",
          "platform_name": "澎湃新闻",
          "rank": 15,
          "title": "日本陆上自卫队一训练场弹药爆炸，2人死亡1人昏迷",
          "url": "https://www.thepaper.cn/newsDetail_forward_33016657"
        },
        {
          "platform_id": "thepaper",
          "platform_name": "澎湃新闻",
          "rank": 16,
          "title": "云南瑞丽市蓝天救援队副队长陈延寿在哈巴雪山救援任务中牺牲",
          "url": "https://www.thepaper.cn/newsDetail_forward_33015802"
        },
        {
          "platform_id": "thepaper",
          "platform_name": "澎湃新闻",
          "rank": 17,
          "title": "一图看懂｜特朗普执政一年后，美国科学界面临什么困境",
          "url": "https://www.thepaper.cn/newsDetail_forward_33015762"
        },
        {
          "platform_id": "thepaper",
          "platform_name": "澎湃新闻",
          "rank": 18,
          "title": "人民日报批“领导没发话，我们不能动”：不沾责任、不沾风险、不沾矛盾",
          "url": "https://www.thepaper.cn/newsDetail_forward_33015016"
        },
        {
          "platform_id": "thepaper",
          "platform_name": "澎湃新闻",
          "rank": 19,
          "title": "“老头乐”成急救送血车？天津市血液中心否认系该单位车辆：正联合相关部门处理",
          "url": "https://www.thepaper.cn/newsDetail_forward_33018263"
        },
        {
          "platform_id": "thepaper",
          "platform_name": "澎湃新闻",
          "rank": 20,
          "title": "河北曲周一KTV服务员被指强奸14岁女生，案件已移交检方",
          "url": "https://www.thepaper.cn/newsDetail_forward_33018848"
        },
        {
          "platform_id": "bilibili-hot-search",
          "platform_name": "哔哩哔哩",
          "rank": 1,
          "title": "《崩坏：星穹铁道》银狼LV.999角色PV——「我独自满级」",
          "url": "https://www.bilibili.com/video/BV1wYdWB5EVF"
        },
        {
          "platform_id": "bilibili-hot-search",
          "platform_name": "哔哩哔哩",
          "rank": 2,
          "title": "口技表演《三打白骨精》",
          "url": "https://www.bilibili.com/video/BV1CVdVBjETn"
        },
        {
          "platform_id": "bilibili-hot-search",
          "platform_name": "哔哩哔哩",
          "rank": 3,
          "title": "\"每次生日许的愿 其实都与你有关\"2.0",
          "url": "https://www.bilibili.com/video/BV1yedxBnEn3"
        },
        {
          "platform_id": "bilibili-hot-search",
          "platform_name": "哔哩哔哩",
          "rank": 4,
          "title": "当你穿进老钱班22",
          "url": "https://www.bilibili.com/video/BV1YQdWBcEtN"
        },
        {
          "platform_id": "bilibili-hot-search",
          "platform_name": "哔哩哔哩",
          "rank": 5,
          "title": "见面5秒开始战斗",
          "url": "https://www.bilibili.com/video/BV1EWdfBTEGy"
        },
        {
          "platform_id": "bilibili-hot-search",
          "platform_name": "哔哩哔哩",
          "rank": 6,
          "title": "疑似三打白骨精现场真实画面流出",
          "url": "https://www.bilibili.com/video/BV11ZdJB6ECR"
        },
        {
          "platform_id": "bilibili-hot-search",
          "platform_name": "哔哩哔哩",
          "rank": 7,
          "title": "刘巳道重拍《哭声》：怀疑即有罪，神明皆恶鬼，万般抉择，皆赴既定终局  /  上集",
          "url": "https://www.bilibili.com/video/BV1uYdRByEXX"
        },
        {
          "platform_id": "bilibili-hot-search",
          "platform_name": "哔哩哔哩",
          "rank": 8,
          "title": "《异环》公测PV丨Play on！",
          "url": "https://www.bilibili.com/video/BV1dsQnB7EHb"
        },
        {
          "platform_id": "bilibili-hot-search",
          "platform_name": "哔哩哔哩",
          "rank": 9,
          "title": "洛天依 原创《告死鸟》",
          "url": "https://www.bilibili.com/video/BV1Y2oNB1ESs"
        },
        {
          "platform_id": "bilibili-hot-search",
          "platform_name": "哔哩哔哩",
          "rank": 10,
          "title": "全明星登场无限城！无惨；你们都是什么柱？！",
          "url": "https://www.bilibili.com/video/BV17Cd5B1E8P"
        },
        {
          "platform_id": "bilibili-hot-search",
          "platform_name": "哔哩哔哩",
          "rank": 11,
          "title": "重庆|如画一般",
          "url": "https://www.bilibili.com/video/BV1BCdZBeECE"
        },
        {
          "platform_id": "bilibili-hot-search",
          "platform_name": "哔哩哔哩",
          "rank": 12,
          "title": "《非法组队》",
          "url": "https://www.bilibili.com/video/BV1QTdHBpEfR"
        },
        {
          "platform_id": "bilibili-hot-search",
          "platform_name": "哔哩哔哩",
          "rank": 13,
          "title": "［meme］豌豆公主",
          "url": "https://www.bilibili.com/video/BV1DNd7BMEqP"
        },
        {
          "platform_id": "bilibili-hot-search",
          "platform_name": "哔哩哔哩",
          "rank": 14,
          "title": "青年大学习初入社会学校不教，但你要会的53个技能",
          "url": "https://www.bilibili.com/video/BV1TTdBBtEtt"
        },
        {
          "platform_id": "bilibili-hot-search",
          "platform_name": "哔哩哔哩",
          "rank": 15,
          "title": "5分钟看完不结婚的一生，到底是什么样子？—自制AI短片",
          "url": "https://www.bilibili.com/video/BV1amdJB7EzS"
        },
        {
          "platform_id": "bilibili-hot-search",
          "platform_name": "哔哩哔哩",
          "rank": 16,
          "title": "《明日方舟：终末地》过场动画 - 却海",
          "url": "https://www.bilibili.com/video/BV1vgd5BMEsG"
        },
        {
          "platform_id": "bilibili-hot-search",
          "platform_name": "哔哩哔哩",
          "rank": 17,
          "title": "点外卖的凑单方式：",
          "url": "https://www.bilibili.com/video/BV1vSdWBaE7b"
        },
        {
          "platform_id": "bilibili-hot-search",
          "platform_name": "哔哩哔哩",
          "rank": 18,
          "title": "破产大王如何搞发明？【小约翰】",
          "url": "https://www.bilibili.com/video/BV1ewdhBmEux"
        },
        {
          "platform_id": "bilibili-hot-search",
          "platform_name": "哔哩哔哩",
          "rank": 19,
          "title": "美国伊朗真乃卧龙凤雏",
          "url": "https://www.bilibili.com/video/BV1Uzd1BUEAS"
        },
        {
          "platform_id": "bilibili-hot-search",
          "platform_name": "哔哩哔哩",
          "rank": 20,
          "title": "楚人美游记 1-5 合集：当楚人美被孙悟空拐去取经",
          "url": "https://www.bilibili.com/video/BV15YdBB6Efz"
        },
        {
          "platform_id": "bilibili-hot-search",
          "platform_name": "哔哩哔哩",
          "rank": 21,
          "title": "“什么叫惊喜”？",
          "url": "https://www.bilibili.com/video/BV1vSdWBaEwz"
        },
        {
          "platform_id": "bilibili-hot-search",
          "platform_name": "哔哩哔哩",
          "rank": 22,
          "title": "语文老师看到都释怀了",
          "url": "https://www.bilibili.com/video/BV1GHdEBjEQT"
        },
        {
          "platform_id": "bilibili-hot-search",
          "platform_name": "哔哩哔哩",
          "rank": 23,
          "title": "【萌黄一槽】志村团藏[漂泊寻者]全技能爆料！这次他做了“十”手准备……",
          "url": "https://www.bilibili.com/video/BV12woKBvEuz"
        },
        {
          "platform_id": "bilibili-hot-search",
          "platform_name": "哔哩哔哩",
          "rank": 24,
          "title": "《重返未来：1999》三周年特别版本·3.7版本PV：他者的悲哀",
          "url": "https://www.bilibili.com/video/BV1MPdBB8EEN"
        },
        {
          "platform_id": "bilibili-hot-search",
          "platform_name": "哔哩哔哩",
          "rank": 25,
          "title": "二舅彻底退场！",
          "url": "https://www.bilibili.com/video/BV1xJoNBPEey"
        },
        {
          "platform_id": "bilibili-hot-search",
          "platform_name": "哔哩哔哩",
          "rank": 26,
          "title": "如果你不会当父母，那我的建议是别生",
          "url": "https://www.bilibili.com/video/BV1kBoFB1EGp"
        },
        {
          "platform_id": "bilibili-hot-search",
          "platform_name": "哔哩哔哩",
          "rank": 27,
          "title": "郝 哥 不 在",
          "url": "https://www.bilibili.com/video/BV1RwdhBmE3M"
        },
        {
          "platform_id": "bilibili-hot-search",
          "platform_name": "哔哩哔哩",
          "rank": 28,
          "title": "【登陆少年】2026TOP登陆少年组合·浪漫主义·演唱会Day1·苏新皓个人直拍",
          "url": "https://www.bilibili.com/video/BV1ffdoBeECC"
        },
        {
          "platform_id": "bilibili-hot-search",
          "platform_name": "哔哩哔哩",
          "rank": 29,
          "title": "老实了，能不能送我回去",
          "url": "https://www.bilibili.com/video/BV1fcdZBAEwk"
        },
        {
          "platform_id": "bilibili-hot-search",
          "platform_name": "哔哩哔哩",
          "rank": 30,
          "title": "火柴人 VS 我的世界 第三十九集 天境（The Aether）",
          "url": "https://www.bilibili.com/video/BV1e8dsBNEB1"
        },
        {
          "platform_id": "bilibili-hot-search",
          "platform_name": "哔哩哔哩",
          "rank": 31,
          "title": "当被问到每天在学校都干些啥时......",
          "url": "https://www.bilibili.com/video/BV1bdddBmEo4"
        },
        {
          "platform_id": "bilibili-hot-search",
          "platform_name": "哔哩哔哩",
          "rank": 32,
          "title": "16名高级军官, 14人做错!德国联邦国防军指挥学院战术真题！【题库】",
          "url": "https://www.bilibili.com/video/BV1uAdBBcEXb"
        },
        {
          "platform_id": "bilibili-hot-search",
          "platform_name": "哔哩哔哩",
          "rank": 33,
          "title": "八年情侣博主的心里话",
          "url": "https://www.bilibili.com/video/BV1uidoBnEiy"
        },
        {
          "platform_id": "bilibili-hot-search",
          "platform_name": "哔哩哔哩",
          "rank": 34,
          "title": "在美国，我们不说“苦中作乐”，我们说...",
          "url": "https://www.bilibili.com/video/BV14zdnBkEU1"
        },
        {
          "platform_id": "bilibili-hot-search",
          "platform_name": "哔哩哔哩",
          "rank": 35,
          "title": "数学这东西，还得跟你田老师学！",
          "url": "https://www.bilibili.com/video/BV1R7oPB1EZM"
        },
        {
          "platform_id": "bilibili-hot-search",
          "platform_name": "哔哩哔哩",
          "rank": 36,
          "title": "成为高启强第一步：卖水产",
          "url": "https://www.bilibili.com/video/BV1m1dVBsEtW"
        },
        {
          "platform_id": "bilibili-hot-search",
          "platform_name": "哔哩哔哩",
          "rank": 37,
          "title": "“至此，神性已成！！！”",
          "url": "https://www.bilibili.com/video/BV1iwoTBWEvc"
        },
        {
          "platform_id": "bilibili-hot-search",
          "platform_name": "哔哩哔哩",
          "rank": 38,
          "title": "【何同学】为了随地大小坐，我们做了这个…",
          "url": "https://www.bilibili.com/video/BV1YydJBJEuF"
        },
        {
          "platform_id": "bilibili-hot-search",
          "platform_name": "哔哩哔哩",
          "rank": 39,
          "title": "《生鱼忧患 死鱼安乐》",
          "url": "https://www.bilibili.com/video/BV1vBd7B1EVL"
        },
        {
          "platform_id": "bilibili-hot-search",
          "platform_name": "哔哩哔哩",
          "rank": 40,
          "title": "喝奶茶",
          "url": "https://www.bilibili.com/video/BV1CTdpBGEbA"
        },
        {
          "platform_id": "bilibili-hot-search",
          "platform_name": "哔哩哔哩",
          "rank": 41,
          "title": "不 死 人 买 瓜",
          "url": "https://www.bilibili.com/video/BV1ZKoFBqEAi"
        },
        {
          "platform_id": "bilibili-hot-search",
          "platform_name": "哔哩哔哩",
          "rank": 42,
          "title": "不该进爷爷的房间的······",
          "url": "https://www.bilibili.com/video/BV1DDdJBLEWa"
        },
        {
          "platform_id": "bilibili-hot-search",
          "platform_name": "哔哩哔哩",
          "rank": 43,
          "title": "工地摆摊",
          "url": "https://www.bilibili.com/video/BV19kd9BUE9D"
        },
        {
          "platform_id": "bilibili-hot-search",
          "platform_name": "哔哩哔哩",
          "rank": 44,
          "title": "小派蒙别害怕，姐姐带你回家~",
          "url": "https://www.bilibili.com/video/BV1BCdZBeEyx"
        },
        {
          "platform_id": "bilibili-hot-search",
          "platform_name": "哔哩哔哩",
          "rank": 45,
          "title": "重生之大坝老鼠当总裁",
          "url": "https://www.bilibili.com/video/BV1SbowB8EuV"
        },
        {
          "platform_id": "bilibili-hot-search",
          "platform_name": "哔哩哔哩",
          "rank": 46,
          "title": "靠刮刮乐成为百万富翁?!!!",
          "url": "https://www.bilibili.com/video/BV1URdJBkEtY"
        },
        {
          "platform_id": "bilibili-hot-search",
          "platform_name": "哔哩哔哩",
          "rank": 47,
          "title": "庄方宜：你看又急",
          "url": "https://www.bilibili.com/video/BV134oPB6EuU"
        },
        {
          "platform_id": "bilibili-hot-search",
          "platform_name": "哔哩哔哩",
          "rank": 48,
          "title": "ZTALK | 第三季爆料特别篇",
          "url": "https://www.bilibili.com/video/BV1mkd1B2E9n"
        },
        {
          "platform_id": "bilibili-hot-search",
          "platform_name": "哔哩哔哩",
          "rank": 49,
          "title": "老婆让我滚出去睡...但是两个老婆 ！2.0",
          "url": "https://www.bilibili.com/video/BV1PadxBXE59"
        },
        {
          "platform_id": "bilibili-hot-search",
          "platform_name": "哔哩哔哩",
          "rank": 50,
          "title": "广西乡村寻狗之人在囧途！",
          "url": "https://www.bilibili.com/video/BV14Xd7BKEGW"
        },
        {
          "platform_id": "bilibili-hot-search",
          "platform_name": "哔哩哔哩",
          "rank": 51,
          "title": "【奇迹男孩1998】我的最新作品，快来一睹为快！",
          "url": "https://www.bilibili.com/video/BV1pCdrB8EPb"
        },
        {
          "platform_id": "bilibili-hot-search",
          "platform_name": "哔哩哔哩",
          "rank": 52,
          "title": "《老友》 年少时，我们以为好朋友是“一起玩”。中年时，我们才懂好朋友是“拉一把”。",
          "url": "https://www.bilibili.com/video/BV16NdzBmE5q"
        },
        {
          "platform_id": "bilibili-hot-search",
          "platform_name": "哔哩哔哩",
          "rank": 53,
          "title": "盒饭有价，但你们的善意是无价的 #阿伟工地摆摊 #工地摆摊 #八元腐竹烧鸭",
          "url": "https://www.bilibili.com/video/BV1s2dpB1E26"
        },
        {
          "platform_id": "bilibili-hot-search",
          "platform_name": "哔哩哔哩",
          "rank": 54,
          "title": "我这辈子最爱的，是戴着头盔的你",
          "url": "https://www.bilibili.com/video/BV1h5oTBLEr4"
        },
        {
          "platform_id": "bilibili-hot-search",
          "platform_name": "哔哩哔哩",
          "rank": 55,
          "title": "烟头叔叔原版VS鬼畜版",
          "url": "https://www.bilibili.com/video/BV1CddBB9EmU"
        },
        {
          "platform_id": "bilibili-hot-search",
          "platform_name": "哔哩哔哩",
          "rank": 56,
          "title": "如果你见到小时候的自己，那么你会做什么？",
          "url": "https://www.bilibili.com/video/BV1rndLBJEkt"
        },
        {
          "platform_id": "bilibili-hot-search",
          "platform_name": "哔哩哔哩",
          "rank": 57,
          "title": "没有知识储备量进了山胡球吃就得噶",
          "url": "https://www.bilibili.com/video/BV1kgdoBMEmm"
        },
        {
          "platform_id": "bilibili-hot-search",
          "platform_name": "哔哩哔哩",
          "rank": 58,
          "title": "人，时代大变了",
          "url": "https://www.bilibili.com/video/BV1Z2dZBaEF9"
        },
        {
          "platform_id": "bilibili-hot-search",
          "platform_name": "哔哩哔哩",
          "rank": 59,
          "title": "【STN快报第8.5季2】宝可梦大师总是会败在夺冠的最后一步",
          "url": "https://www.bilibili.com/video/BV1Q5dZBWEeD"
        },
        {
          "platform_id": "bilibili-hot-search",
          "platform_name": "哔哩哔哩",
          "rank": 60,
          "title": "红狼新赛季隐藏皮肤：离家出走的腿",
          "url": "https://www.bilibili.com/video/BV1e9dxBqEQR"
        },
        {
          "platform_id": "bilibili-hot-search",
          "platform_name": "哔哩哔哩",
          "rank": 61,
          "title": "我要修改这个结局！",
          "url": "https://www.bilibili.com/video/BV146oKBzErX"
        },
        {
          "platform_id": "bilibili-hot-search",
          "platform_name": "哔哩哔哩",
          "rank": 62,
          "title": "精油开背仁王盾",
          "url": "https://www.bilibili.com/video/BV1FDdnBNEXF"
        },
        {
          "platform_id": "bilibili-hot-search",
          "platform_name": "哔哩哔哩",
          "rank": 63,
          "title": "新西兰夯爆了！",
          "url": "https://www.bilibili.com/video/BV1j6oNBSE9V"
        },
        {
          "platform_id": "bilibili-hot-search",
          "platform_name": "哔哩哔哩",
          "rank": 64,
          "title": "我是律师，请用当事人的语气让我破防14.0",
          "url": "https://www.bilibili.com/video/BV1scdnBBEMg"
        },
        {
          "platform_id": "bilibili-hot-search",
          "platform_name": "哔哩哔哩",
          "rank": 65,
          "title": "这把给两人都演爽了",
          "url": "https://www.bilibili.com/video/BV1pgdoBME4t"
        },
        {
          "platform_id": "bilibili-hot-search",
          "platform_name": "哔哩哔哩",
          "rank": 66,
          "title": "“当别人问我这辈子什么时候最紧张”",
          "url": "https://www.bilibili.com/video/BV1TmdfBDEau"
        },
        {
          "platform_id": "bilibili-hot-search",
          "platform_name": "哔哩哔哩",
          "rank": 67,
          "title": "驻日使馆公开的“杀光支那人”威胁信全面详解",
          "url": "https://www.bilibili.com/video/BV1ASdoBrEGm"
        },
        {
          "platform_id": "bilibili-hot-search",
          "platform_name": "哔哩哔哩",
          "rank": 68,
          "title": "新游戏到了，有人要来我家玩吗？",
          "url": "https://www.bilibili.com/video/BV1E4dBByE7o"
        },
        {
          "platform_id": "bilibili-hot-search",
          "platform_name": "哔哩哔哩",
          "rank": 69,
          "title": "学了三天特效做出来的昔涟技能动画",
          "url": "https://www.bilibili.com/video/BV12UdVBpEtg"
        },
        {
          "platform_id": "bilibili-hot-search",
          "platform_name": "哔哩哔哩",
          "rank": 70,
          "title": "右转三次变左转，旁人因果旁人担！万字拉片拆解 烧脑日恐《不安的种子》",
          "url": "https://www.bilibili.com/video/BV1iidJBREm9"
        },
        {
          "platform_id": "bilibili-hot-search",
          "platform_name": "哔哩哔哩",
          "rank": 71,
          "title": "樱花雨",
          "url": "https://www.bilibili.com/video/BV1CkdnB6EZm"
        },
        {
          "platform_id": "bilibili-hot-search",
          "platform_name": "哔哩哔哩",
          "rank": 72,
          "title": "淀粉肠臭豆腐烤冷面 火遍全国的小吃是怎么诞生的？",
          "url": "https://www.bilibili.com/video/BV1G4dnBDEb1"
        },
        {
          "platform_id": "bilibili-hot-search",
          "platform_name": "哔哩哔哩",
          "rank": 73,
          "title": "自助餐的迷惑行为",
          "url": "https://www.bilibili.com/video/BV158doBsEYF"
        },
        {
          "platform_id": "bilibili-hot-search",
          "platform_name": "哔哩哔哩",
          "rank": 74,
          "title": "人类史上第一次买瓜",
          "url": "https://www.bilibili.com/video/BV1ZvdkB9EXV"
        },
        {
          "platform_id": "bilibili-hot-search",
          "platform_name": "哔哩哔哩",
          "rank": 75,
          "title": "【这不是ai！】假如我是宝石人｜无人声敲击音ASMR",
          "url": "https://www.bilibili.com/video/BV1KpdHBVEzq"
        },
        {
          "platform_id": "bilibili-hot-search",
          "platform_name": "哔哩哔哩",
          "rank": 76,
          "title": "【速凌宇宙】第十六集：赛伊德带队入侵航天？勇者行动开启！",
          "url": "https://www.bilibili.com/video/BV1CbdHBMEHK"
        },
        {
          "platform_id": "bilibili-hot-search",
          "platform_name": "哔哩哔哩",
          "rank": 77,
          "title": "气氛逐渐和谐",
          "url": "https://www.bilibili.com/video/BV1tWdqBoEvy"
        },
        {
          "platform_id": "bilibili-hot-search",
          "platform_name": "哔哩哔哩",
          "rank": 78,
          "title": "顶级智斗",
          "url": "https://www.bilibili.com/video/BV16wdjBHErh"
        },
        {
          "platform_id": "bilibili-hot-search",
          "platform_name": "哔哩哔哩",
          "rank": 79,
          "title": "我们俩#郭顶#翻唱清唱，今天和媳妇商量拍个视频",
          "url": "https://www.bilibili.com/video/BV1f9dnBwEeb"
        },
        {
          "platform_id": "bilibili-hot-search",
          "platform_name": "哔哩哔哩",
          "rank": 80,
          "title": "逆天小游戏2215",
          "url": "https://www.bilibili.com/video/BV1EYdhB4EfK"
        },
        {
          "platform_id": "bilibili-hot-search",
          "platform_name": "哔哩哔哩",
          "rank": 81,
          "title": "【灵笼修仙传】-凡人灵笼-新的起点",
          "url": "https://www.bilibili.com/video/BV1cfdsBLEHE"
        },
        {
          "platform_id": "bilibili-hot-search",
          "platform_name": "哔哩哔哩",
          "rank": 82,
          "title": "你的辩论固然惊艳，但你的人生更胜一筹",
          "url": "https://www.bilibili.com/video/BV1HCdzBQESr"
        },
        {
          "platform_id": "bilibili-hot-search",
          "platform_name": "哔哩哔哩",
          "rank": 83,
          "title": "公开悬赏！所有玩家为了赏金不择手段？！！「列车狼人杀」",
          "url": "https://www.bilibili.com/video/BV1tWdWBnEv4"
        },
        {
          "platform_id": "bilibili-hot-search",
          "platform_name": "哔哩哔哩",
          "rank": 84,
          "title": "当然是陪她一起玩啦",
          "url": "https://www.bilibili.com/video/BV1WcdnBBEZB"
        },
        {
          "platform_id": "bilibili-hot-search",
          "platform_name": "哔哩哔哩",
          "rank": 85,
          "title": "霍尔木兹开关开关，下半场怎么打？【岛岛连线xAJ小外】",
          "url": "https://www.bilibili.com/video/BV14WoTBuExc"
        },
        {
          "platform_id": "bilibili-hot-search",
          "platform_name": "哔哩哔哩",
          "rank": 86,
          "title": "沙鹰转枪灭队，豪到你了吗《沙鹰颗秒21.0》",
          "url": "https://www.bilibili.com/video/BV1q5drBJEw8"
        },
        {
          "platform_id": "bilibili-hot-search",
          "platform_name": "哔哩哔哩",
          "rank": 87,
          "title": "聂菲斯：同事全是神人怎么玩",
          "url": "https://www.bilibili.com/video/BV1HLdsByEco"
        },
        {
          "platform_id": "bilibili-hot-search",
          "platform_name": "哔哩哔哩",
          "rank": 88,
          "title": "以防你不知道兔兔已经有97套衣服！？阿米娅的colors~2026ver.~",
          "url": "https://www.bilibili.com/video/BV16vdHBPEtA"
        },
        {
          "platform_id": "bilibili-hot-search",
          "platform_name": "哔哩哔哩",
          "rank": 89,
          "title": "从知名童星到互联网抽象圣体？盘点嘎子直播间究极抽象名场面！看完笑疯了哈哈哈",
          "url": "https://www.bilibili.com/video/BV1GtdpBZEx8"
        },
        {
          "platform_id": "bilibili-hot-search",
          "platform_name": "哔哩哔哩",
          "rank": 90,
          "title": "和李现，攀登人生第一座雪山",
          "url": "https://www.bilibili.com/video/BV1SSQLBREVV"
        },
        {
          "platform_id": "bilibili-hot-search",
          "platform_name": "哔哩哔哩",
          "rank": 91,
          "title": "好听吗？好听就是好头！让狼宝用头演奏Cyberangel",
          "url": "https://www.bilibili.com/video/BV1kidZBuE7e"
        },
        {
          "platform_id": "bilibili-hot-search",
          "platform_name": "哔哩哔哩",
          "rank": 92,
          "title": "家里有这种“诱惑”，谁还出门儿呀！",
          "url": "https://www.bilibili.com/video/BV1SUdJB2Eid"
        },
        {
          "platform_id": "bilibili-hot-search",
          "platform_name": "哔哩哔哩",
          "rank": 93,
          "title": "《狗不理》",
          "url": "https://www.bilibili.com/video/BV199dZBoEw1"
        },
        {
          "platform_id": "bilibili-hot-search",
          "platform_name": "哔哩哔哩",
          "rank": 94,
          "title": "press词根记单词，体验飞一般的感觉",
          "url": "https://www.bilibili.com/video/BV1UVdJB6Eg2"
        },
        {
          "platform_id": "bilibili-hot-search",
          "platform_name": "哔哩哔哩",
          "rank": 95,
          "title": "刀都断了 凭什么夺冠？《锻刀大赛》疯癫赛制 还说不是黑幕！",
          "url": "https://www.bilibili.com/video/BV1c6d5BmE3E"
        },
        {
          "platform_id": "bilibili-hot-search",
          "platform_name": "哔哩哔哩",
          "rank": 96,
          "title": "野外生存小技巧",
          "url": "https://www.bilibili.com/video/BV1C8dWBjE1f"
        },
        {
          "platform_id": "bilibili-hot-search",
          "platform_name": "哔哩哔哩",
          "rank": 97,
          "title": "百事能做到吗？！",
          "url": "https://www.bilibili.com/video/BV1HCdzBQECF"
        },
        {
          "platform_id": "bilibili-hot-search",
          "platform_name": "哔哩哔哩",
          "rank": 98,
          "title": "10星罗隐解放大脑，快速启动，贪婪一开直接开打",
          "url": "https://www.bilibili.com/video/BV1MWdZBEE2t"
        },
        {
          "platform_id": "bilibili-hot-search",
          "platform_name": "哔哩哔哩",
          "rank": 99,
          "title": "黑幕、皇族、德不配位其实浪姐1就有，那《浪姐 1》凭什么依旧能封神？！",
          "url": "https://www.bilibili.com/video/BV1G7djB3E56"
        },
        {
          "platform_id": "bilibili-hot-search",
          "platform_name": "哔哩哔哩",
          "rank": 100,
          "title": "火腿肠实力排行",
          "url": "https://www.bilibili.com/video/BV1uadnB7Evg"
        },
        {
          "platform_id": "tieba",
          "platform_name": "百度贴吧",
          "rank": 1,
          "title": "伊朗将恢复国内航班运营",
          "url": "https://tieba.baidu.com/hottopic/browse/hottopic?topic_id=28353546&amp;topic_name=%E4%BC%8A%E6%9C%97%E5%B0%86%E6%81%A2%E5%A4%8D%E5%9B%BD%E5%86%85%E8%88%AA%E7%8F%AD%E8%BF%90%E8%90%A5"
        },
        {
          "platform_id": "tieba",
          "platform_name": "百度贴吧",
          "rank": 2,
          "title": "人多味大!偶像劝粉丝勤搓澡",
          "url": "https://tieba.baidu.com/hottopic/browse/hottopic?topic_id=28353549&amp;topic_name=%E4%BA%BA%E5%A4%9A%E5%91%B3%E5%A4%A7%21%E5%81%B6%E5%83%8F%E5%8A%9D%E7%B2%89%E4%B8%9D%E5%8B%A4%E6%90%93%E6%BE%A1"
        },
        {
          "platform_id": "tieba",
          "platform_name": "百度贴吧",
          "rank": 3,
          "title": "老人打赏棺材本,330万不心疼",
          "url": "https://tieba.baidu.com/hottopic/browse/hottopic?topic_id=28353543&amp;topic_name=%E8%80%81%E4%BA%BA%E6%89%93%E8%B5%8F%E6%A3%BA%E6%9D%90%E6%9C%AC%2C330%E4%B8%87%E4%B8%8D%E5%BF%83%E7%96%BC"
        },
        {
          "platform_id": "tieba",
          "platform_name": "百度贴吧",
          "rank": 4,
          "title": "紫薇再现神评,惹米游玩家围攻",
          "url": "https://tieba.baidu.com/hottopic/browse/hottopic?topic_id=28353550&amp;topic_name=%E7%B4%AB%E8%96%87%E5%86%8D%E7%8E%B0%E7%A5%9E%E8%AF%84%2C%E6%83%B9%E7%B1%B3%E6%B8%B8%E7%8E%A9%E5%AE%B6%E5%9B%B4%E6%94%BB"
        },
        {
          "platform_id": "tieba",
          "platform_name": "百度贴吧",
          "rank": 5,
          "title": "南大考研爆雷,220分上985",
          "url": "https://tieba.baidu.com/hottopic/browse/hottopic?topic_id=28353551&amp;topic_name=%E5%8D%97%E5%A4%A7%E8%80%83%E7%A0%94%E7%88%86%E9%9B%B7%2C220%E5%88%86%E4%B8%8A985"
        },
        {
          "platform_id": "tieba",
          "platform_name": "百度贴吧",
          "rank": 6,
          "title": "伟大无需多言!风月赛后狂吹JKL",
          "url": "https://tieba.baidu.com/hottopic/browse/hottopic?topic_id=28353545&amp;topic_name=%E4%BC%9F%E5%A4%A7%E6%97%A0%E9%9C%80%E5%A4%9A%E8%A8%80%21%E9%A3%8E%E6%9C%88%E8%B5%9B%E5%90%8E%E7%8B%82%E5%90%B9JKL"
        },
        {
          "platform_id": "tieba",
          "platform_name": "百度贴吧",
          "rank": 7,
          "title": "美国启动一万亿元退关税",
          "url": "https://tieba.baidu.com/hottopic/browse/hottopic?topic_id=28353548&amp;topic_name=%E7%BE%8E%E5%9B%BD%E5%90%AF%E5%8A%A8%E4%B8%80%E4%B8%87%E4%BA%BF%E5%85%83%E9%80%80%E5%85%B3%E7%A8%8E"
        },
        {
          "platform_id": "tieba",
          "platform_name": "百度贴吧",
          "rank": 8,
          "title": "挪千万打赏主播,榜一:不追款",
          "url": "https://tieba.baidu.com/hottopic/browse/hottopic?topic_id=28353505&amp;topic_name=%E6%8C%AA%E5%8D%83%E4%B8%87%E6%89%93%E8%B5%8F%E4%B8%BB%E6%92%AD%2C%E6%A6%9C%E4%B8%80%3A%E4%B8%8D%E8%BF%BD%E6%AC%BE"
        },
        {
          "platform_id": "tieba",
          "platform_name": "百度贴吧",
          "rank": 9,
          "title": "顶级嘲讽,LPL笑看图刷屏",
          "url": "https://tieba.baidu.com/hottopic/browse/hottopic?topic_id=28353502&amp;topic_name=%E9%A1%B6%E7%BA%A7%E5%98%B2%E8%AE%BD%2CLPL%E7%AC%91%E7%9C%8B%E5%9B%BE%E5%88%B7%E5%B1%8F"
        },
        {
          "platform_id": "tieba",
          "platform_name": "百度贴吧",
          "rank": 10,
          "title": "维权不手软,00后整顿一切",
          "url": "https://tieba.baidu.com/hottopic/browse/hottopic?topic_id=28353535&amp;topic_name=%E7%BB%B4%E6%9D%83%E4%B8%8D%E6%89%8B%E8%BD%AF%2C00%E5%90%8E%E6%95%B4%E9%A1%BF%E4%B8%80%E5%88%87"
        },
        {
          "platform_id": "tieba",
          "platform_name": "百度贴吧",
          "rank": 11,
          "title": "美国男子枪杀8名儿童后自戕",
          "url": "https://tieba.baidu.com/hottopic/browse/hottopic?topic_id=28353501&amp;topic_name=%E7%BE%8E%E5%9B%BD%E7%94%B7%E5%AD%90%E6%9E%AA%E6%9D%808%E5%90%8D%E5%84%BF%E7%AB%A5%E5%90%8E%E8%87%AA%E6%88%95"
        },
        {
          "platform_id": "tieba",
          "platform_name": "百度贴吧",
          "rank": 12,
          "title": "霸王助阵文旅,宿迁热度空前",
          "url": "https://tieba.baidu.com/hottopic/browse/hottopic?topic_id=28353526&amp;topic_name=%E9%9C%B8%E7%8E%8B%E5%8A%A9%E9%98%B5%E6%96%87%E6%97%85%2C%E5%AE%BF%E8%BF%81%E7%83%AD%E5%BA%A6%E7%A9%BA%E5%89%8D"
        },
        {
          "platform_id": "tieba",
          "platform_name": "百度贴吧",
          "rank": 13,
          "title": "版权卫士vs盗版王,日俄网友开撕",
          "url": "https://tieba.baidu.com/hottopic/browse/hottopic?topic_id=28353498&amp;topic_name=%E7%89%88%E6%9D%83%E5%8D%AB%E5%A3%ABvs%E7%9B%97%E7%89%88%E7%8E%8B%2C%E6%97%A5%E4%BF%84%E7%BD%91%E5%8F%8B%E5%BC%80%E6%92%95"
        },
        {
          "platform_id": "tieba",
          "platform_name": "百度贴吧",
          "rank": 14,
          "title": "触手捅穿主角,国漫真敢拍",
          "url": "https://tieba.baidu.com/hottopic/browse/hottopic?topic_id=28353507&amp;topic_name=%E8%A7%A6%E6%89%8B%E6%8D%85%E7%A9%BF%E4%B8%BB%E8%A7%92%2C%E5%9B%BD%E6%BC%AB%E7%9C%9F%E6%95%A2%E6%8B%8D"
        },
        {
          "platform_id": "tieba",
          "platform_name": "百度贴吧",
          "rank": 15,
          "title": "洛克惊现大佬,死磕稀有异宠",
          "url": "https://tieba.baidu.com/hottopic/browse/hottopic?topic_id=28353536&amp;topic_name=%E6%B4%9B%E5%85%8B%E6%83%8A%E7%8E%B0%E5%A4%A7%E4%BD%AC%2C%E6%AD%BB%E7%A3%95%E7%A8%80%E6%9C%89%E5%BC%82%E5%AE%A0"
        },
        {
          "platform_id": "tieba",
          "platform_name": "百度贴吧",
          "rank": 16,
          "title": "日本开发新脑洞:机器人拆开做",
          "url": "https://tieba.baidu.com/hottopic/browse/hottopic?topic_id=28353542&amp;topic_name=%E6%97%A5%E6%9C%AC%E5%BC%80%E5%8F%91%E6%96%B0%E8%84%91%E6%B4%9E%3A%E6%9C%BA%E5%99%A8%E4%BA%BA%E6%8B%86%E5%BC%80%E5%81%9A"
        },
        {
          "platform_id": "tieba",
          "platform_name": "百度贴吧",
          "rank": 17,
          "title": "10式坦克炸膛,3人重伤至死",
          "url": "https://tieba.baidu.com/hottopic/browse/hottopic?topic_id=28353532&amp;topic_name=10%E5%BC%8F%E5%9D%A6%E5%85%8B%E7%82%B8%E8%86%9B%2C3%E4%BA%BA%E9%87%8D%E4%BC%A4%E8%87%B3%E6%AD%BB"
        },
        {
          "platform_id": "tieba",
          "platform_name": "百度贴吧",
          "rank": 18,
          "title": "go学长区别对待,lol倒大霉",
          "url": "https://tieba.baidu.com/hottopic/browse/hottopic?topic_id=28353541&amp;topic_name=go%E5%AD%A6%E9%95%BF%E5%8C%BA%E5%88%AB%E5%AF%B9%E5%BE%85%2Clol%E5%80%92%E5%A4%A7%E9%9C%89"
        },
        {
          "platform_id": "tieba",
          "platform_name": "百度贴吧",
          "rank": 19,
          "title": "这阵容也行?BLG断送IG中东路",
          "url": "https://tieba.baidu.com/hottopic/browse/hottopic?topic_id=28353496&amp;topic_name=%E8%BF%99%E9%98%B5%E5%AE%B9%E4%B9%9F%E8%A1%8C%3FBLG%E6%96%AD%E9%80%81IG%E4%B8%AD%E4%B8%9C%E8%B7%AF"
        },
        {
          "platform_id": "tieba",
          "platform_name": "百度贴吧",
          "rank": 20,
          "title": "吧友装机被骗,boot收费500",
          "url": "https://tieba.baidu.com/hottopic/browse/hottopic?topic_id=28353482&amp;topic_name=%E5%90%A7%E5%8F%8B%E8%A3%85%E6%9C%BA%E8%A2%AB%E9%AA%97%2Cboot%E6%94%B6%E8%B4%B9500"
        },
        {
          "platform_id": "tieba",
          "platform_name": "百度贴吧",
          "rank": 21,
          "title": "换帅!苹果高管迎来大洗牌",
          "url": "https://tieba.baidu.com/hottopic/browse/hottopic?topic_id=28353506&amp;topic_name=%E6%8D%A2%E5%B8%85%21%E8%8B%B9%E6%9E%9C%E9%AB%98%E7%AE%A1%E8%BF%8E%E6%9D%A5%E5%A4%A7%E6%B4%97%E7%89%8C"
        },
        {
          "platform_id": "tieba",
          "platform_name": "百度贴吧",
          "rank": 22,
          "title": "蜜蜂官推玩梗致donk被开团",
          "url": "https://tieba.baidu.com/hottopic/browse/hottopic?topic_id=28353514&amp;topic_name=%E8%9C%9C%E8%9C%82%E5%AE%98%E6%8E%A8%E7%8E%A9%E6%A2%97%E8%87%B4donk%E8%A2%AB%E5%BC%80%E5%9B%A2"
        },
        {
          "platform_id": "tieba",
          "platform_name": "百度贴吧",
          "rank": 23,
          "title": "up主力挺王者世界遭群嘲",
          "url": "https://tieba.baidu.com/hottopic/browse/hottopic?topic_id=28353468&amp;topic_name=up%E4%B8%BB%E5%8A%9B%E6%8C%BA%E7%8E%8B%E8%80%85%E4%B8%96%E7%95%8C%E9%81%AD%E7%BE%A4%E5%98%B2"
        },
        {
          "platform_id": "tieba",
          "platform_name": "百度贴吧",
          "rank": 24,
          "title": "日本火锅肉薄如纸,1盘不够塞牙",
          "url": "https://tieba.baidu.com/hottopic/browse/hottopic?topic_id=28353492&amp;topic_name=%E6%97%A5%E6%9C%AC%E7%81%AB%E9%94%85%E8%82%89%E8%96%84%E5%A6%82%E7%BA%B8%2C1%E7%9B%98%E4%B8%8D%E5%A4%9F%E5%A1%9E%E7%89%99"
        },
        {
          "platform_id": "tieba",
          "platform_name": "百度贴吧",
          "rank": 25,
          "title": "角色疑遭暗削,玩家求助籽岷",
          "url": "https://tieba.baidu.com/hottopic/browse/hottopic?topic_id=28353475&amp;topic_name=%E8%A7%92%E8%89%B2%E7%96%91%E9%81%AD%E6%9A%97%E5%89%8A%2C%E7%8E%A9%E5%AE%B6%E6%B1%82%E5%8A%A9%E7%B1%BD%E5%B2%B7"
        },
        {
          "platform_id": "tieba",
          "platform_name": "百度贴吧",
          "rank": 26,
          "title": "准入门槛更新,异环直接爆",
          "url": "https://tieba.baidu.com/hottopic/browse/hottopic?topic_id=28353478&amp;topic_name=%E5%87%86%E5%85%A5%E9%97%A8%E6%A7%9B%E6%9B%B4%E6%96%B0%2C%E5%BC%82%E7%8E%AF%E7%9B%B4%E6%8E%A5%E7%88%86"
        },
        {
          "platform_id": "tieba",
          "platform_name": "百度贴吧",
          "rank": 27,
          "title": "榜一挪用千万公款打赏主播",
          "url": "https://tieba.baidu.com/hottopic/browse/hottopic?topic_id=28353497&amp;topic_name=%E6%A6%9C%E4%B8%80%E6%8C%AA%E7%94%A8%E5%8D%83%E4%B8%87%E5%85%AC%E6%AC%BE%E6%89%93%E8%B5%8F%E4%B8%BB%E6%92%AD"
        },
        {
          "platform_id": "tieba",
          "platform_name": "百度贴吧",
          "rank": 28,
          "title": "AI围剿影视圈,演员签卖身契",
          "url": "https://tieba.baidu.com/hottopic/browse/hottopic?topic_id=28353493&amp;topic_name=AI%E5%9B%B4%E5%89%BF%E5%BD%B1%E8%A7%86%E5%9C%88%2C%E6%BC%94%E5%91%98%E7%AD%BE%E5%8D%96%E8%BA%AB%E5%A5%91"
        },
        {
          "platform_id": "tieba",
          "platform_name": "百度贴吧",
          "rank": 29,
          "title": "孩子被骗纹花臂,家长崩溃",
          "url": "https://tieba.baidu.com/hottopic/browse/hottopic?topic_id=28353486&amp;topic_name=%E5%AD%A9%E5%AD%90%E8%A2%AB%E9%AA%97%E7%BA%B9%E8%8A%B1%E8%87%82%2C%E5%AE%B6%E9%95%BF%E5%B4%A9%E6%BA%83"
        },
        {
          "platform_id": "tieba",
          "platform_name": "百度贴吧",
          "rank": 30,
          "title": "1999限定空降,周年庆惹恼玩家",
          "url": "https://tieba.baidu.com/hottopic/browse/hottopic?topic_id=28353488&amp;topic_name=1999%E9%99%90%E5%AE%9A%E7%A9%BA%E9%99%8D%2C%E5%91%A8%E5%B9%B4%E5%BA%86%E6%83%B9%E6%81%BC%E7%8E%A9%E5%AE%B6"
        },
        {
          "platform_id": "weibo",
          "platform_name": "微博",
          "rank": 1,
          "title": "男子心脏停跳2天后生还",
          "url": "https://s.weibo.com/weibo?q=%E7%94%B7%E5%AD%90%E5%BF%83%E8%84%8F%E5%81%9C%E8%B7%B32%E5%A4%A9%E5%90%8E%E7%94%9F%E8%BF%98"
        },
        {
          "platform_id": "weibo",
          "platform_name": "微博",
          "rank": 2,
          "title": "巴萨",
          "url": "https://s.weibo.com/weibo?q=%E5%B7%B4%E8%90%A8"
        },
        {
          "platform_id": "weibo",
          "platform_name": "微博",
          "rank": 3,
          "title": "中国工业成绩单亮了",
          "url": "https://s.weibo.com/weibo?q=%E4%B8%AD%E5%9B%BD%E5%B7%A5%E4%B8%9A%E6%88%90%E7%BB%A9%E5%8D%95%E4%BA%AE%E4%BA%86"
        },
        {
          "platform_id": "weibo",
          "platform_name": "微博",
          "rank": 4,
          "title": "和吴磊一骑保护地球",
          "url": "https://s.weibo.com/weibo?q=%E5%92%8C%E5%90%B4%E7%A3%8A%E4%B8%80%E9%AA%91%E4%BF%9D%E6%8A%A4%E5%9C%B0%E7%90%83"
        },
        {
          "platform_id": "weibo",
          "platform_name": "微博",
          "rank": 5,
          "title": "伊朗储油罐要满了",
          "url": "https://s.weibo.com/weibo?q=%E4%BC%8A%E6%9C%97%E5%82%A8%E6%B2%B9%E7%BD%90%E8%A6%81%E6%BB%A1%E4%BA%86"
        },
        {
          "platform_id": "weibo",
          "platform_name": "微博",
          "rank": 6,
          "title": "吃原型食物",
          "url": "https://s.weibo.com/weibo?q=%E5%90%83%E5%8E%9F%E5%9E%8B%E9%A3%9F%E7%89%A9"
        },
        {
          "platform_id": "weibo",
          "platform_name": "微博",
          "rank": 7,
          "title": "乐道L90价格",
          "url": "https://s.weibo.com/weibo?q=%E4%B9%90%E9%81%93L90%E4%BB%B7%E6%A0%BC"
        },
        {
          "platform_id": "weibo",
          "platform_name": "微博",
          "rank": 8,
          "title": "转飞猪抢票符 冲徐良南昌站",
          "url": "https://s.weibo.com/weibo?q=%E8%BD%AC%E9%A3%9E%E7%8C%AA%E6%8A%A2%E7%A5%A8%E7%AC%A6%20%E5%86%B2%E5%BE%90%E8%89%AF%E5%8D%97%E6%98%8C%E7%AB%99"
        },
        {
          "platform_id": "weibo",
          "platform_name": "微博",
          "rank": 9,
          "title": "唐诡导演 真人能演为啥让AI演",
          "url": "https://s.weibo.com/weibo?q=%E5%94%90%E8%AF%A1%E5%AF%BC%E6%BC%94%20%E7%9C%9F%E4%BA%BA%E8%83%BD%E6%BC%94%E4%B8%BA%E5%95%A5%E8%AE%A9AI%E6%BC%94"
        },
        {
          "platform_id": "weibo",
          "platform_name": "微博",
          "rank": 10,
          "title": "义乌请量产吧",
          "url": "https://s.weibo.com/weibo?q=%E4%B9%89%E4%B9%8C%E8%AF%B7%E9%87%8F%E4%BA%A7%E5%90%A7"
        },
        {
          "platform_id": "weibo",
          "platform_name": "微博",
          "rank": 11,
          "title": "董力给阿诺发全职妈妈工资",
          "url": "https://s.weibo.com/weibo?q=%E8%91%A3%E5%8A%9B%E7%BB%99%E9%98%BF%E8%AF%BA%E5%8F%91%E5%85%A8%E8%81%8C%E5%A6%88%E5%A6%88%E5%B7%A5%E8%B5%84"
        },
        {
          "platform_id": "weibo",
          "platform_name": "微博",
          "rank": 12,
          "title": "上海海港vs重庆铜梁龙",
          "url": "https://s.weibo.com/weibo?q=%E4%B8%8A%E6%B5%B7%E6%B5%B7%E6%B8%AFvs%E9%87%8D%E5%BA%86%E9%93%9C%E6%A2%81%E9%BE%99"
        },
        {
          "platform_id": "weibo",
          "platform_name": "微博",
          "rank": 13,
          "title": "杨蓉面部烫伤恢复近照",
          "url": "https://s.weibo.com/weibo?q=%E6%9D%A8%E8%93%89%E9%9D%A2%E9%83%A8%E7%83%AB%E4%BC%A4%E6%81%A2%E5%A4%8D%E8%BF%91%E7%85%A7"
        },
        {
          "platform_id": "weibo",
          "platform_name": "微博",
          "rank": 14,
          "title": "白鹿给助理呵呵做饭",
          "url": "https://s.weibo.com/weibo?q=%E7%99%BD%E9%B9%BF%E7%BB%99%E5%8A%A9%E7%90%86%E5%91%B5%E5%91%B5%E5%81%9A%E9%A5%AD"
        },
        {
          "platform_id": "weibo",
          "platform_name": "微博",
          "rank": 15,
          "title": "虞书欣新歌",
          "url": "https://s.weibo.com/weibo?q=%E8%99%9E%E4%B9%A6%E6%AC%A3%E6%96%B0%E6%AD%8C"
        },
        {
          "platform_id": "weibo",
          "platform_name": "微博",
          "rank": 16,
          "title": "挪用1700万打赏女生发声",
          "url": "https://s.weibo.com/weibo?q=%E6%8C%AA%E7%94%A81700%E4%B8%87%E6%89%93%E8%B5%8F%E5%A5%B3%E7%94%9F%E5%8F%91%E5%A3%B0"
        },
        {
          "platform_id": "weibo",
          "platform_name": "微博",
          "rank": 17,
          "title": "姚晨为救护车改道去世女子发声",
          "url": "https://s.weibo.com/weibo?q=%E5%A7%9A%E6%99%A8%E4%B8%BA%E6%95%91%E6%8A%A4%E8%BD%A6%E6%94%B9%E9%81%93%E5%8E%BB%E4%B8%96%E5%A5%B3%E5%AD%90%E5%8F%91%E5%A3%B0"
        },
        {
          "platform_id": "weibo",
          "platform_name": "微博",
          "rank": 18,
          "title": "亚足联认定马宁亚冠判罚公正",
          "url": "https://s.weibo.com/weibo?q=%E4%BA%9A%E8%B6%B3%E8%81%94%E8%AE%A4%E5%AE%9A%E9%A9%AC%E5%AE%81%E4%BA%9A%E5%86%A0%E5%88%A4%E7%BD%9A%E5%85%AC%E6%AD%A3"
        },
        {
          "platform_id": "weibo",
          "platform_name": "微博",
          "rank": 19,
          "title": "贝克汉姆回复50米吊射破门高中生",
          "url": "https://s.weibo.com/weibo?q=%E8%B4%9D%E5%85%8B%E6%B1%89%E5%A7%86%E5%9B%9E%E5%A4%8D50%E7%B1%B3%E5%90%8A%E5%B0%84%E7%A0%B4%E9%97%A8%E9%AB%98%E4%B8%AD%E7%94%9F"
        },
        {
          "platform_id": "weibo",
          "platform_name": "微博",
          "rank": 20,
          "title": "光明日报发虞书欣新歌",
          "url": "https://s.weibo.com/weibo?q=%E5%85%89%E6%98%8E%E6%97%A5%E6%8A%A5%E5%8F%91%E8%99%9E%E4%B9%A6%E6%AC%A3%E6%96%B0%E6%AD%8C"
        },
        {
          "platform_id": "weibo",
          "platform_name": "微博",
          "rank": 21,
          "title": "人与人最大的区别就是出门",
          "url": "https://s.weibo.com/weibo?q=%E4%BA%BA%E4%B8%8E%E4%BA%BA%E6%9C%80%E5%A4%A7%E7%9A%84%E5%8C%BA%E5%88%AB%E5%B0%B1%E6%98%AF%E5%87%BA%E9%97%A8"
        },
        {
          "platform_id": "weibo",
          "platform_name": "微博",
          "rank": 22,
          "title": "肯德基多要酱收费",
          "url": "https://s.weibo.com/weibo?q=%E8%82%AF%E5%BE%B7%E5%9F%BA%E5%A4%9A%E8%A6%81%E9%85%B1%E6%94%B6%E8%B4%B9"
        },
        {
          "platform_id": "weibo",
          "platform_name": "微博",
          "rank": 23,
          "title": "迅猛龙开付费直播",
          "url": "https://s.weibo.com/weibo?q=%E8%BF%85%E7%8C%9B%E9%BE%99%E5%BC%80%E4%BB%98%E8%B4%B9%E7%9B%B4%E6%92%AD"
        },
        {
          "platform_id": "weibo",
          "platform_name": "微博",
          "rank": 24,
          "title": "时代少年团 团体工作室",
          "url": "https://s.weibo.com/weibo?q=%E6%97%B6%E4%BB%A3%E5%B0%91%E5%B9%B4%E5%9B%A2%20%E5%9B%A2%E4%BD%93%E5%B7%A5%E4%BD%9C%E5%AE%A4"
        },
        {
          "platform_id": "weibo",
          "platform_name": "微博",
          "rank": 25,
          "title": "OPPO哈苏双两亿影像给到夯",
          "url": "https://s.weibo.com/weibo?q=OPPO%E5%93%88%E8%8B%8F%E5%8F%8C%E4%B8%A4%E4%BA%BF%E5%BD%B1%E5%83%8F%E7%BB%99%E5%88%B0%E5%A4%AF"
        },
        {
          "platform_id": "weibo",
          "platform_name": "微博",
          "rank": 26,
          "title": "宁德时代吴凯称多化学体系是必选项",
          "url": "https://s.weibo.com/weibo?q=%E5%AE%81%E5%BE%B7%E6%97%B6%E4%BB%A3%E5%90%B4%E5%87%AF%E7%A7%B0%E5%A4%9A%E5%8C%96%E5%AD%A6%E4%BD%93%E7%B3%BB%E6%98%AF%E5%BF%85%E9%80%89%E9%A1%B9"
        },
        {
          "platform_id": "weibo",
          "platform_name": "微博",
          "rank": 27,
          "title": "女子拍下日本地震时画面",
          "url": "https://s.weibo.com/weibo?q=%E5%A5%B3%E5%AD%90%E6%8B%8D%E4%B8%8B%E6%97%A5%E6%9C%AC%E5%9C%B0%E9%9C%87%E6%97%B6%E7%94%BB%E9%9D%A2"
        },
        {
          "platform_id": "weibo",
          "platform_name": "微博",
          "rank": 28,
          "title": "沙溢玩嗨了李斌有诚意",
          "url": "https://s.weibo.com/weibo?q=%E6%B2%99%E6%BA%A2%E7%8E%A9%E5%97%A8%E4%BA%86%E6%9D%8E%E6%96%8C%E6%9C%89%E8%AF%9A%E6%84%8F"
        },
        {
          "platform_id": "weibo",
          "platform_name": "微博",
          "rank": 29,
          "title": "张翰回应去移民局",
          "url": "https://s.weibo.com/weibo?q=%E5%BC%A0%E7%BF%B0%E5%9B%9E%E5%BA%94%E5%8E%BB%E7%A7%BB%E6%B0%91%E5%B1%80"
        },
        {
          "platform_id": "weibo",
          "platform_name": "微博",
          "rank": 30,
          "title": "遭老板性侵女子主张应赔付250余万",
          "url": "https://s.weibo.com/weibo?q=%E9%81%AD%E8%80%81%E6%9D%BF%E6%80%A7%E4%BE%B5%E5%A5%B3%E5%AD%90%E4%B8%BB%E5%BC%A0%E5%BA%94%E8%B5%94%E4%BB%98250%E4%BD%99%E4%B8%87"
        },
        {
          "platform_id": "weibo",
          "platform_name": "微博",
          "rank": 31,
          "title": "哪吒造车3年烧掉183亿",
          "url": "https://s.weibo.com/weibo?q=%E5%93%AA%E5%90%92%E9%80%A0%E8%BD%A63%E5%B9%B4%E7%83%A7%E6%8E%89183%E4%BA%BF"
        },
        {
          "platform_id": "weibo",
          "platform_name": "微博",
          "rank": 32,
          "title": "吴磊的骑行故事",
          "url": "https://s.weibo.com/weibo?q=%E5%90%B4%E7%A3%8A%E7%9A%84%E9%AA%91%E8%A1%8C%E6%95%85%E4%BA%8B"
        },
        {
          "platform_id": "weibo",
          "platform_name": "微博",
          "rank": 33,
          "title": "宁德时代",
          "url": "https://s.weibo.com/weibo?q=%E5%AE%81%E5%BE%B7%E6%97%B6%E4%BB%A3"
        },
        {
          "platform_id": "weibo",
          "platform_name": "微博",
          "rank": 34,
          "title": "浪胃仙自曝整容失败",
          "url": "https://s.weibo.com/weibo?q=%E6%B5%AA%E8%83%83%E4%BB%99%E8%87%AA%E6%9B%9D%E6%95%B4%E5%AE%B9%E5%A4%B1%E8%B4%A5"
        },
        {
          "platform_id": "weibo",
          "platform_name": "微博",
          "rank": 35,
          "title": "垫底辣孩与路人合照状态",
          "url": "https://s.weibo.com/weibo?q=%E5%9E%AB%E5%BA%95%E8%BE%A3%E5%AD%A9%E4%B8%8E%E8%B7%AF%E4%BA%BA%E5%90%88%E7%85%A7%E7%8A%B6%E6%80%81"
        },
        {
          "platform_id": "weibo",
          "platform_name": "微博",
          "rank": 36,
          "title": "14岁女生被KTV服务员强奸母亲发声",
          "url": "https://s.weibo.com/weibo?q=14%E5%B2%81%E5%A5%B3%E7%94%9F%E8%A2%ABKTV%E6%9C%8D%E5%8A%A1%E5%91%98%E5%BC%BA%E5%A5%B8%E6%AF%8D%E4%BA%B2%E5%8F%91%E5%A3%B0"
        },
        {
          "platform_id": "weibo",
          "platform_name": "微博",
          "rank": 37,
          "title": "李荣浩直播手机掉水里了",
          "url": "https://s.weibo.com/weibo?q=%E6%9D%8E%E8%8D%A3%E6%B5%A9%E7%9B%B4%E6%92%AD%E6%89%8B%E6%9C%BA%E6%8E%89%E6%B0%B4%E9%87%8C%E4%BA%86"
        },
        {
          "platform_id": "weibo",
          "platform_name": "微博",
          "rank": 38,
          "title": "郭晓婷王天辰 夫妻相",
          "url": "https://s.weibo.com/weibo?q=%E9%83%AD%E6%99%93%E5%A9%B7%E7%8E%8B%E5%A4%A9%E8%BE%B0%20%E5%A4%AB%E5%A6%BB%E7%9B%B8"
        },
        {
          "platform_id": "weibo",
          "platform_name": "微博",
          "rank": 39,
          "title": "小伙养6个弟妹又有7弟外婆发声",
          "url": "https://s.weibo.com/weibo?q=%E5%B0%8F%E4%BC%99%E5%85%BB6%E4%B8%AA%E5%BC%9F%E5%A6%B9%E5%8F%88%E6%9C%897%E5%BC%9F%E5%A4%96%E5%A9%86%E5%8F%91%E5%A3%B0"
        },
        {
          "platform_id": "weibo",
          "platform_name": "微博",
          "rank": 40,
          "title": "业内评价白鹿",
          "url": "https://s.weibo.com/weibo?q=%E4%B8%9A%E5%86%85%E8%AF%84%E4%BB%B7%E7%99%BD%E9%B9%BF"
        },
        {
          "platform_id": "weibo",
          "platform_name": "微博",
          "rank": 41,
          "title": "孙俪儿子画个妆直接能演甄嬛了",
          "url": "https://s.weibo.com/weibo?q=%E5%AD%99%E4%BF%AA%E5%84%BF%E5%AD%90%E7%94%BB%E4%B8%AA%E5%A6%86%E7%9B%B4%E6%8E%A5%E8%83%BD%E6%BC%94%E7%94%84%E5%AC%9B%E4%BA%86"
        },
        {
          "platform_id": "weibo",
          "platform_name": "微博",
          "rank": 42,
          "title": "张继科说祖国荣誉高于一切",
          "url": "https://s.weibo.com/weibo?q=%E5%BC%A0%E7%BB%A7%E7%A7%91%E8%AF%B4%E7%A5%96%E5%9B%BD%E8%8D%A3%E8%AA%89%E9%AB%98%E4%BA%8E%E4%B8%80%E5%88%87"
        },
        {
          "platform_id": "weibo",
          "platform_name": "微博",
          "rank": 43,
          "title": "孙艺洲模仿李小冉心愿便利贴",
          "url": "https://s.weibo.com/weibo?q=%E5%AD%99%E8%89%BA%E6%B4%B2%E6%A8%A1%E4%BB%BF%E6%9D%8E%E5%B0%8F%E5%86%89%E5%BF%83%E6%84%BF%E4%BE%BF%E5%88%A9%E8%B4%B4"
        },
        {
          "platform_id": "weibo",
          "platform_name": "微博",
          "rank": 44,
          "title": "丁程鑫裸半身游泳",
          "url": "https://s.weibo.com/weibo?q=%E4%B8%81%E7%A8%8B%E9%91%AB%E8%A3%B8%E5%8D%8A%E8%BA%AB%E6%B8%B8%E6%B3%B3"
        },
        {
          "platform_id": "weibo",
          "platform_name": "微博",
          "rank": 45,
          "title": "身上出现肉疙瘩警惕这4种瘤",
          "url": "https://s.weibo.com/weibo?q=%E8%BA%AB%E4%B8%8A%E5%87%BA%E7%8E%B0%E8%82%89%E7%96%99%E7%98%A9%E8%AD%A6%E6%83%95%E8%BF%994%E7%A7%8D%E7%98%A4"
        },
        {
          "platform_id": "weibo",
          "platform_name": "微博",
          "rank": 46,
          "title": "邓紫棋改编周杰伦的爱琴海",
          "url": "https://s.weibo.com/weibo?q=%E9%82%93%E7%B4%AB%E6%A3%8B%E6%94%B9%E7%BC%96%E5%91%A8%E6%9D%B0%E4%BC%A6%E7%9A%84%E7%88%B1%E7%90%B4%E6%B5%B7"
        },
        {
          "platform_id": "weibo",
          "platform_name": "微博",
          "rank": 47,
          "title": "窈窈有期第一集硬刚第二集删除",
          "url": "https://s.weibo.com/weibo?q=%E7%AA%88%E7%AA%88%E6%9C%89%E6%9C%9F%E7%AC%AC%E4%B8%80%E9%9B%86%E7%A1%AC%E5%88%9A%E7%AC%AC%E4%BA%8C%E9%9B%86%E5%88%A0%E9%99%A4"
        },
        {
          "platform_id": "weibo",
          "platform_name": "微博",
          "rank": 48,
          "title": "老外回国后得连夜写篇意林",
          "url": "https://s.weibo.com/weibo?q=%E8%80%81%E5%A4%96%E5%9B%9E%E5%9B%BD%E5%90%8E%E5%BE%97%E8%BF%9E%E5%A4%9C%E5%86%99%E7%AF%87%E6%84%8F%E6%9E%97"
        },
        {
          "platform_id": "weibo",
          "platform_name": "微博",
          "rank": 49,
          "title": "官方通报南昌虐婴事件",
          "url": "https://s.weibo.com/weibo?q=%E5%AE%98%E6%96%B9%E9%80%9A%E6%8A%A5%E5%8D%97%E6%98%8C%E8%99%90%E5%A9%B4%E4%BA%8B%E4%BB%B6"
        },
        {
          "platform_id": "weibo",
          "platform_name": "微博",
          "rank": 50,
          "title": "蜜语纪",
          "url": "https://s.weibo.com/weibo?q=%E8%9C%9C%E8%AF%AD%E7%BA%AA"
        },
        {
          "platform_id": "weibo",
          "platform_name": "微博",
          "rank": 51,
          "title": "杨幂冯湮儿太后微服私访",
          "url": "https://s.weibo.com/weibo?q=%E6%9D%A8%E5%B9%82%E5%86%AF%E6%B9%AE%E5%84%BF%E5%A4%AA%E5%90%8E%E5%BE%AE%E6%9C%8D%E7%A7%81%E8%AE%BF"
        },
        {
          "platform_id": "weibo",
          "platform_name": "微博",
          "rank": 52,
          "title": "父母再生7弟20岁小伙直言扛不动",
          "url": "https://s.weibo.com/weibo?q=%E7%88%B6%E6%AF%8D%E5%86%8D%E7%94%9F7%E5%BC%9F20%E5%B2%81%E5%B0%8F%E4%BC%99%E7%9B%B4%E8%A8%80%E6%89%9B%E4%B8%8D%E5%8A%A8"
        },
        {
          "platform_id": "douyin",
          "platform_name": "抖音",
          "rank": 1,
          "title": "国内油价迎2026年首次下调",
          "url": "https://www.douyin.com/hot/2473493"
        },
        {
          "platform_id": "douyin",
          "platform_name": "抖音",
          "rank": 2,
          "title": "非遗穿进日常的N种方式",
          "url": "https://www.douyin.com/hot/2473653"
        },
        {
          "platform_id": "douyin",
          "platform_name": "抖音",
          "rank": 3,
          "title": "全国5G基站总数已达495.8万个",
          "url": "https://www.douyin.com/hot/2474107"
        },
        {
          "platform_id": "douyin",
          "platform_name": "抖音",
          "rank": 4,
          "title": "第13批在韩志愿军烈士遗骸将回国",
          "url": "https://www.douyin.com/hot/2473404"
        },
        {
          "platform_id": "douyin",
          "platform_name": "抖音",
          "rank": 5,
          "title": "中国代表当场驳斥美方攻击抹黑",
          "url": "https://www.douyin.com/hot/2473370"
        },
        {
          "platform_id": "douyin",
          "platform_name": "抖音",
          "rank": 6,
          "title": "云南的目瑙纵歌节场面太震撼了",
          "url": "https://www.douyin.com/hot/2472402"
        },
        {
          "platform_id": "douyin",
          "platform_name": "抖音",
          "rank": 7,
          "title": "江苏为什么能把苏超玩出新花样",
          "url": "https://www.douyin.com/hot/2473534"
        },
        {
          "platform_id": "douyin",
          "platform_name": "抖音",
          "rank": 8,
          "title": "山城的巷子里满是人间烟火",
          "url": "https://www.douyin.com/hot/2472256"
        },
        {
          "platform_id": "douyin",
          "platform_name": "抖音",
          "rank": 9,
          "title": "裙摆一扬夏天登场",
          "url": "https://www.douyin.com/hot/2472509"
        },
        {
          "platform_id": "douyin",
          "platform_name": "抖音",
          "rank": 10,
          "title": "大湾区首台华龙核电机组投运",
          "url": "https://www.douyin.com/hot/2473708"
        },
        {
          "platform_id": "douyin",
          "platform_name": "抖音",
          "rank": 11,
          "title": "湖北涉黑头目黄大发被判死刑",
          "url": "https://www.douyin.com/hot/2473873"
        },
        {
          "platform_id": "douyin",
          "platform_name": "抖音",
          "rank": 12,
          "title": "日本10式坦克炸膛事故细节公布",
          "url": "https://www.douyin.com/hot/2474315"
        },
        {
          "platform_id": "douyin",
          "platform_name": "抖音",
          "rank": 13,
          "title": "独牙传奇赛：杨绍杰战胜薛珍麒",
          "url": "https://www.douyin.com/hot/2474081"
        },
        {
          "platform_id": "douyin",
          "platform_name": "抖音",
          "rank": 14,
          "title": "王毅将访问柬埔寨泰国缅甸",
          "url": "https://www.douyin.com/hot/2473941"
        },
        {
          "platform_id": "douyin",
          "platform_name": "抖音",
          "rank": 15,
          "title": "猪价开启“回暖”模式",
          "url": "https://www.douyin.com/hot/2473583"
        },
        {
          "platform_id": "douyin",
          "platform_name": "抖音",
          "rank": 16,
          "title": "印度加快推进苹果反垄断案",
          "url": "https://www.douyin.com/hot/2473570"
        },
        {
          "platform_id": "douyin",
          "platform_name": "抖音",
          "rank": 17,
          "title": "石油价格上涨或导致维生素变贵",
          "url": "https://www.douyin.com/hot/2473529"
        },
        {
          "platform_id": "douyin",
          "platform_name": "抖音",
          "rank": 18,
          "title": "媒体评日本军舰穿越台湾海峡",
          "url": "https://www.douyin.com/hot/2473187"
        },
        {
          "platform_id": "douyin",
          "platform_name": "抖音",
          "rank": 19,
          "title": "女朋友唱的专属bgm",
          "url": "https://www.douyin.com/hot/2473674"
        },
        {
          "platform_id": "douyin",
          "platform_name": "抖音",
          "rank": 20,
          "title": "星铁银狼角色动画",
          "url": "https://www.douyin.com/hot/2473958"
        },
        {
          "platform_id": "douyin",
          "platform_name": "抖音",
          "rank": 21,
          "title": "怦然照愉崩溃大哭好心疼",
          "url": "https://www.douyin.com/hot/2473726"
        },
        {
          "platform_id": "douyin",
          "platform_name": "抖音",
          "rank": 22,
          "title": "内容由爱生成",
          "url": "https://www.douyin.com/hot/2472818"
        },
        {
          "platform_id": "douyin",
          "platform_name": "抖音",
          "rank": 23,
          "title": "自动剥葡萄机的含金量有多高",
          "url": "https://www.douyin.com/hot/2474389"
        },
        {
          "platform_id": "douyin",
          "platform_name": "抖音",
          "rank": 24,
          "title": "李荣浩直播手机掉水里了",
          "url": "https://www.douyin.com/hot/2474274"
        },
        {
          "platform_id": "douyin",
          "platform_name": "抖音",
          "rank": 25,
          "title": "拨开天空的乌云情侣转场",
          "url": "https://www.douyin.com/hot/2472791"
        },
        {
          "platform_id": "douyin",
          "platform_name": "抖音",
          "rank": 26,
          "title": "何润东项羽造型亮相苏超观后感",
          "url": "https://www.douyin.com/hot/2472445"
        },
        {
          "platform_id": "douyin",
          "platform_name": "抖音",
          "rank": 27,
          "title": "左奇函ego手势舞好萌",
          "url": "https://www.douyin.com/hot/2474236"
        },
        {
          "platform_id": "douyin",
          "platform_name": "抖音",
          "rank": 28,
          "title": "火影手游漂泊团藏全技能爆料",
          "url": "https://www.douyin.com/hot/2473120"
        },
        {
          "platform_id": "douyin",
          "platform_name": "抖音",
          "rank": 29,
          "title": "陈赫演老父亲看哭李乃文",
          "url": "https://www.douyin.com/hot/2473781"
        },
        {
          "platform_id": "douyin",
          "platform_name": "抖音",
          "rank": 30,
          "title": "被人砍了一剑咋这么疼呢",
          "url": "https://www.douyin.com/hot/2473045"
        },
        {
          "platform_id": "douyin",
          "platform_name": "抖音",
          "rank": 31,
          "title": "Beauty And A Beat杀回来了",
          "url": "https://www.douyin.com/hot/2473832"
        },
        {
          "platform_id": "douyin",
          "platform_name": "抖音",
          "rank": 32,
          "title": "怦然女六粥粥好清醒的发言",
          "url": "https://www.douyin.com/hot/2473756"
        },
        {
          "platform_id": "douyin",
          "platform_name": "抖音",
          "rank": 33,
          "title": "回答一下我的钱花哪了",
          "url": "https://www.douyin.com/hot/2473891"
        },
        {
          "platform_id": "douyin",
          "platform_name": "抖音",
          "rank": 34,
          "title": "贵州烧烤大排档真的不一样",
          "url": "https://www.douyin.com/hot/2473297"
        },
        {
          "platform_id": "douyin",
          "platform_name": "抖音",
          "rank": 35,
          "title": "一人之下八奇技的由来",
          "url": "https://www.douyin.com/hot/2473301"
        },
        {
          "platform_id": "douyin",
          "platform_name": "抖音",
          "rank": 36,
          "title": "田嘉瑞的精神状态belike",
          "url": "https://www.douyin.com/hot/2473946"
        },
        {
          "platform_id": "douyin",
          "platform_name": "抖音",
          "rank": 37,
          "title": "IU新剧照镜子转场",
          "url": "https://www.douyin.com/hot/2472731"
        },
        {
          "platform_id": "douyin",
          "platform_name": "抖音",
          "rank": 38,
          "title": "宋雨琦红裙复仇摇好辣",
          "url": "https://www.douyin.com/hot/2474353"
        },
        {
          "platform_id": "douyin",
          "platform_name": "抖音",
          "rank": 39,
          "title": "黑夜告白定档0426",
          "url": "https://www.douyin.com/hot/2473645"
        },
        {
          "platform_id": "douyin",
          "platform_name": "抖音",
          "rank": 40,
          "title": "李梦鲁贞贞有福就享没福硬抢",
          "url": "https://www.douyin.com/hot/2473766"
        },
        {
          "platform_id": "douyin",
          "platform_name": "抖音",
          "rank": 41,
          "title": "任嘉伦王鹤润新剧监狱相亲",
          "url": "https://www.douyin.com/hot/2473585"
        },
        {
          "platform_id": "douyin",
          "platform_name": "抖音",
          "rank": 42,
          "title": "拜托小姐翻拍",
          "url": "https://www.douyin.com/hot/2472218"
        },
        {
          "platform_id": "douyin",
          "platform_name": "抖音",
          "rank": 43,
          "title": "可爱猫咪的治愈瞬间",
          "url": "https://www.douyin.com/hot/2472592"
        },
        {
          "platform_id": "douyin",
          "platform_name": "抖音",
          "rank": 44,
          "title": "刘晓艳打卡重庆机车约拍",
          "url": "https://www.douyin.com/hot/2473104"
        },
        {
          "platform_id": "douyin",
          "platform_name": "抖音",
          "rank": 45,
          "title": "律师谈单依纯新歌造型被指侵权",
          "url": "https://www.douyin.com/hot/2473009"
        },
        {
          "platform_id": "douyin",
          "platform_name": "抖音",
          "rank": 46,
          "title": "有一天也是能靠脸吃饭了",
          "url": "https://www.douyin.com/hot/2472655"
        },
        {
          "platform_id": "douyin",
          "platform_name": "抖音",
          "rank": 47,
          "title": "已经开始期待五一了",
          "url": "https://www.douyin.com/hot/2472534"
        },
        {
          "platform_id": "douyin",
          "platform_name": "抖音",
          "rank": 48,
          "title": "地库跳舞的氛围感被我掌握了",
          "url": "https://www.douyin.com/hot/2472529"
        },
        {
          "platform_id": "douyin",
          "platform_name": "抖音",
          "rank": 49,
          "title": "只喜欢我一个人好不好",
          "url": "https://www.douyin.com/hot/2472563"
        },
        {
          "platform_id": "zhihu",
          "platform_name": "知乎",
          "rank": 1,
          "title": "19 岁女生挪用 1700 万元打赏、买盲盒，家长还能追回这笔钱吗？主播和平台是否有义务退钱？",
          "url": "https://www.zhihu.com/question/2029687631366078518"
        },
        {
          "platform_id": "zhihu",
          "platform_name": "知乎",
          "rank": 2,
          "title": "如何看待北师大学生在图书馆犯困发现 CO₂ 超标，投诉后学校拆除检测仪？这种超标现象常见吗？怎样缓解？",
          "url": "https://www.zhihu.com/question/2029587978876445987"
        },
        {
          "platform_id": "zhihu",
          "platform_name": "知乎",
          "rank": 3,
          "title": "近 70 款车集体降价，新能源平均降 3.8 万，长安汽车总经理称车企仅靠卖车已无法盈利，真是这样吗？",
          "url": "https://www.zhihu.com/question/2029614261630935945"
        },
        {
          "platform_id": "zhihu",
          "platform_name": "知乎",
          "rank": 4,
          "title": "如何看待大厂员工称996辛苦都是演的，每天正经工作时间屈指可数?",
          "url": "https://www.zhihu.com/question/2007571519992272031"
        },
        {
          "platform_id": "zhihu",
          "platform_name": "知乎",
          "rank": 5,
          "title": "十几块的沙县鸡腿饭成了「中国宝宝的减脂神器」，套餐包含鸡腿、米饭和蔬菜，它的优势在哪里？真能减脂吗？",
          "url": "https://www.zhihu.com/question/2027397560780727963"
        },
        {
          "platform_id": "zhihu",
          "platform_name": "知乎",
          "rank": 6,
          "title": "迅雷光鸭云盘永久免费 2TB 且不限速，这会给国内网盘市场带来哪些影响？",
          "url": "https://www.zhihu.com/question/2029107688429109449"
        },
        {
          "platform_id": "zhihu",
          "platform_name": "知乎",
          "rank": 7,
          "title": "如何评价孙杨、张豆豆在《妻子的浪漫旅行 2026》中的表现？",
          "url": "https://www.zhihu.com/question/2025590523440767073"
        },
        {
          "platform_id": "zhihu",
          "platform_name": "知乎",
          "rank": 8,
          "title": "日本通过内阁决议正式允许出口杀伤性武器，这意味着什么？会给东北亚地区带来哪些变化？",
          "url": "https://www.zhihu.com/question/2029848664269419073"
        },
        {
          "platform_id": "zhihu",
          "platform_name": "知乎",
          "rank": 9,
          "title": "《封神 3》正在后期制作，或用 AI 做特效，乌尔善能否逆风翻盘？",
          "url": "https://www.zhihu.com/question/2027797621893244826"
        },
        {
          "platform_id": "zhihu",
          "platform_name": "知乎",
          "rank": 10,
          "title": "为什么《肖申克的救赎》的男主角安迪最后选择跑到芝华塔利欧隐姓埋名而不是利用银行家的才华重出江湖？",
          "url": "https://www.zhihu.com/question/1932973838649505147"
        },
        {
          "platform_id": "zhihu",
          "platform_name": "知乎",
          "rank": 11,
          "title": "如何看待卡尔南开大学二轮调剂被刷？你对他一路调剂、屡次被拒有哪些感慨？",
          "url": "https://www.zhihu.com/question/2028736307036189218"
        },
        {
          "platform_id": "zhihu",
          "platform_name": "知乎",
          "rank": 12,
          "title": "为什么粤菜和西餐一样先上汤后上主菜，而其他菜系通常是上完了菜再上汤？这样的饮食习惯是怎样形成的？",
          "url": "https://www.zhihu.com/question/1913264882180142246"
        },
        {
          "platform_id": "zhihu",
          "platform_name": "知乎",
          "rank": 13,
          "title": "豫剧观众哭成「憋泪哥」，演员称有时自己出不了戏，传统戏曲为何能让人如此动容？",
          "url": "https://www.zhihu.com/question/2027123888006473717"
        },
        {
          "platform_id": "zhihu",
          "platform_name": "知乎",
          "rank": 14,
          "title": "人的记忆可以被移植吗？如果可以，那是否可以实现“一人学会，大家都会”？",
          "url": "https://www.zhihu.com/question/2024706722997052547"
        },
        {
          "platform_id": "zhihu",
          "platform_name": "知乎",
          "rank": 15,
          "title": "婴儿在列车哭闹不止，儿童摄影师三秒哄好，这是什么技巧？网友说「家长需要帮忙而非指责」，如何看待这件事？",
          "url": "https://www.zhihu.com/question/2029589904816875280"
        },
        {
          "platform_id": "zhihu",
          "platform_name": "知乎",
          "rank": 16,
          "title": "美以袭击伊朗进入第 53 天，当前局势如何？还有哪些信息值得关注？",
          "url": "https://www.zhihu.com/question/2029682687414203990"
        },
        {
          "platform_id": "zhihu",
          "platform_name": "知乎",
          "rank": 17,
          "title": "男子被老板骂「滚」后离岗，1 个月后公司以旷工为由解约被判违法，口头指令模糊引发纠纷，企业应如何担责？",
          "url": "https://www.zhihu.com/question/2028123240367702785"
        },
        {
          "platform_id": "zhihu",
          "platform_name": "知乎",
          "rank": 18,
          "title": "库克宣布将于 9 月卸任苹果 CEO，由特努斯接任，哪些信息值得关注？苹果的未来会如何发展？",
          "url": "https://www.zhihu.com/question/2029792979703874483"
        },
        {
          "platform_id": "zhihu",
          "platform_name": "知乎",
          "rank": 19,
          "title": "女子频繁向多人表白后被诊断为精神障碍，这到底是一种什么病？",
          "url": "https://www.zhihu.com/question/2029483780633621016"
        },
        {
          "platform_id": "zhihu",
          "platform_name": "知乎",
          "rank": 20,
          "title": "参加第十七届全国大学生数学竞赛（决赛）是什么体验？如何评价今年的试题？",
          "url": "https://www.zhihu.com/question/2028863332854112494"
        },
        {
          "platform_id": "zhihu",
          "platform_name": "知乎",
          "rank": 21,
          "title": "阿森纳本赛季的结局，最终是双冠、仅英超、仅欧冠、还是四大皆空，哪种可能性最大？",
          "url": "https://www.zhihu.com/question/2029495828054570751"
        },
        {
          "platform_id": "zhihu",
          "platform_name": "知乎",
          "rank": 22,
          "title": "无偿献血证被中介层层倒卖至两千元，献血者仅拿到 400 元营养费，无偿献血证怎么成了一门「生意」？",
          "url": "https://www.zhihu.com/question/2028764235639858321"
        },
        {
          "platform_id": "zhihu",
          "platform_name": "知乎",
          "rank": 23,
          "title": "物业公司大规模撤离小区，此前曾因现金流充沛被视为地产行业的「现金奶牛」，为啥会这样？对业主影响大吗？",
          "url": "https://www.zhihu.com/question/2028162844949066722"
        },
        {
          "platform_id": "zhihu",
          "platform_name": "知乎",
          "rank": 24,
          "title": "幼儿园小朋友每天不想上学，有什么方法能让他理解上学很重要?",
          "url": "https://www.zhihu.com/question/2014652814228472730"
        },
        {
          "platform_id": "zhihu",
          "platform_name": "知乎",
          "rank": 25,
          "title": "最新民调显示，特朗普当前支持率为 37% ，超六成美国人反对扩大对伊军事行动，这一数据意味什么？",
          "url": "https://www.zhihu.com/question/2029573491297395870"
        },
        {
          "platform_id": "zhihu",
          "platform_name": "知乎",
          "rank": 26,
          "title": "为什么虚数ⅰ³=-ⅰ，而(ⅰ⁴)的3/4次幂=1？哪里出问题了？",
          "url": "https://www.zhihu.com/question/668141628"
        },
        {
          "platform_id": "zhihu",
          "platform_name": "知乎",
          "rank": 27,
          "title": "腹式呼吸有什么弊端？",
          "url": "https://www.zhihu.com/question/282174141"
        },
        {
          "platform_id": "zhihu",
          "platform_name": "知乎",
          "rank": 28,
          "title": "如何评价电影《寒战》？",
          "url": "https://www.zhihu.com/question/20587371"
        },
        {
          "platform_id": "zhihu",
          "platform_name": "知乎",
          "rank": 29,
          "title": "奥匈帝国为何不自建一门“普通话”加以推广以解决民族和语言问题？",
          "url": "https://www.zhihu.com/question/356795733"
        },
        {
          "platform_id": "zhihu",
          "platform_name": "知乎",
          "rank": 30,
          "title": "美国释放谈判「热信号」，伊朗给出强硬「冷回应」，一热一冷，到底谁在套路谁？局势将如何发展？",
          "url": "https://www.zhihu.com/question/2029844598520824805"
        }
      ]
    }
  ]
}